pyrasa/__init__.py
pyrasa/__version__.py
pyrasa/irasa.py
pyrasa/py.typed
pyrasa/irasa_mne/__init__.py
pyrasa/irasa_mne/irasa_mne.py
pyrasa/irasa_mne/mne_objs.py
pyrasa/utils/aperiodic_utils.py
pyrasa/utils/fit_funcs.py
pyrasa/utils/irasa_spectrum.py
pyrasa/utils/irasa_tf_spectrum.py
pyrasa/utils/irasa_utils.py
pyrasa/utils/peak_utils.py
pyrasa/utils/types.py
pyrasa-1.1.1.dist-info/METADATA
pyrasa-1.1.1.dist-info/WHEEL
pyrasa-1.1.1.dist-info/licenses/LICENSE
pyrasa-1.1.1.dist-info/RECORD
