Metadata-Version: 2.4
Name: PyRASA
Version: 1.1.1
Summary: Spectral parametrization based on IRASA
Project-URL: repository, https://github.com/schmidtfa/pyrasa
Author-email: Fabian Schmidt <schmidtfa91@gmail.com>, Thomas Hartmann <thomas.hartmann@th-ht.de>
License: BSD-3-Clause
License-File: LICENSE
Keywords: 1/f,oscillations,power spectra,spectral parametrization
Classifier: Development Status :: 4 - Beta
Classifier: Intended Audience :: Science/Research
Classifier: License :: OSI Approved :: BSD License
Classifier: Operating System :: OS Independent
Classifier: Programming Language :: Python
Classifier: Typing :: Typed
Requires-Python: >=3.11
Requires-Dist: attrs
Requires-Dist: numpy<3,>=1.26
Requires-Dist: pandas<3,>=2.1
Requires-Dist: scipy>=1.12
Provides-Extra: mne
Requires-Dist: mne; extra == 'mne'
